mcgpyutils/__init__.py
mcgpyutils/colorUtils.py
mcgpyutils/configUtils.py
mcgpyutils/datetimeUtils.py
mcgpyutils/fileSystemUtils.py
mcgpyutils/googleDriveUtils.py
mcgpyutils/gtmetrixUtils.py
mcgpyutils/outputUtils.py
mcgpyutils/pwfUtils.py
mcgpyutils/slackUtils.py
mcgpyutils-1.0.5.dist-info/DESCRIPTION.rst
mcgpyutils-1.0.5.dist-info/LICENSE.txt
mcgpyutils-1.0.5.dist-info/METADATA
mcgpyutils-1.0.5.dist-info/RECORD
mcgpyutils-1.0.5.dist-info/WHEEL
mcgpyutils-1.0.5.dist-info/metadata.json
mcgpyutils-1.0.5.dist-info/top_level.txt
