Metadata-Version: 2.0
Name: mcgpyutils
Version: 1.0.5
Summary: Common Python utilities used at MCG Strategic
Home-page: https://www.mcgstrategic.com
Author: MCG Strategic
Author-email: support@mcgstrategic.com
License: MIT
Platform: UNKNOWN
Classifier: Intended Audience :: Developers
Classifier: Topic :: Utilities
Classifier: Topic :: Software Development
Classifier: License :: OSI Approved :: MIT License
Classifier: Programming Language :: Python :: 3 :: Only
Classifier: Programming Language :: Python :: 3.6
Requires-Python: >=3.6
Requires-Dist: requests
Requires-Dist: slacker
Requires-Dist: google-api-python-client
